setup.py
xswizard/XenAPI.py
xswizard/__init__.py
xswizard/api.py
xswizard/constants.py
xswizard/exceptions.py
xswizard/models.py
xswizard.egg-info/PKG-INFO
xswizard.egg-info/SOURCES.txt
xswizard.egg-info/dependency_links.txt
xswizard.egg-info/top_level.txt